{"id": 21, "created": 1403031451, "votes": 28, "title": "Varsiselleri", "state": "APPROVED", "slug": "varsiselleri", "body": "Kiellet\u00e4\u00e4n varsisellerin k\u00e4ytt\u00f6 keitoissa, koska se pilaa keiton kuin keiton maun. Erityisen ongelmalliseksi sen k\u00e4yt\u00f6n tekee sen, ett\u00e4 k\u00e4yt\u00f6st\u00e4 saa varmuuden vasta maistamalla. Kylm\u00e4n\u00e4 talvip\u00e4iv\u00e4n\u00e4 on suuri pettymys, kun ravintolassa tai ty\u00f6paikkaruokalassa iloitsee ensin l\u00e4mpim\u00e4st\u00e4 keitosta ja sitten maistaessa huomaa, ett\u00e4 se on pilattu varsisellerill\u00e4. \n\nWalldorffin salaatissa sit\u00e4 saa edelleen k\u00e4ytt\u00e4\u00e4, koska se on perinneruoka. Salaatin v\u00e4litt\u00f6m\u00e4ss\u00e4 l\u00e4heisyydess\u00e4 tai pakkauksessa t\u00e4ytyy kuitenkin olla varoitusmerkint\u00e4 varsisellerin k\u00e4yt\u00f6st\u00e4.", "user_name": "Kari Rajala", "user_city": "Turku"}