{"id": 63, "created": 1403075642, "votes": 3, "title": "Omistaminen", "state": "APPROVED", "slug": "omistaminen", "body": "Ei ole oikein, ett\u00e4 muut omistavat mit\u00e4\u00e4n. Olisi parasta, ett\u00e4 kaikki olisi yhteist\u00e4. Sit\u00e4 voidaan hallinnoida hyvin hallitusti sitten. Suurin osa ei osaa hallinnoida, joten olisi parasta, ett\u00e4 min\u00e4, aloitteen is\u00e4, olisin mukana hallinnon puheenjohtajistossa. \n( Koska muut hallinnon tyypit ovat niin hankalia, ja hallinto on niin haastavaa ja v a s t u u l l i s t a, hallinnolle t\u00e4ytyy perustaessa taata tarvittavat resurssit. Mukaan lukien kansainv\u00e4lisen tason palkkiot. )", "user_name": "Antti", "user_city": "Helsinki"}